orchid66.py
x11_colors.py
orchid66-1.1.6.dist-info/METADATA
orchid66-1.1.6.dist-info/WHEEL
orchid66-1.1.6.dist-info/top_level.txt
orchid66-1.1.6.dist-info/RECORD
