Metadata-Version: 2.1
Name: orchid66
Version: 1.1.6
Summary: print in color easily!
Home-page: https://github.com/therealadityashankar/orchid66
Author: Aditya Shankar
Author-email: aditniru@gmail.com
License: MIT
Platform: UNKNOWN
Classifier: License :: OSI Approved :: MIT License
Classifier: Programming Language :: Python :: 3
Classifier: Programming Language :: Python :: 3.7
